performance_analysis/.DS_Store
performance_analysis/Constant.py
performance_analysis/Performance.py
performance_analysis/Plotting.py
performance_analysis/__init__.py
performance_analysis-0.1.0.dist-info/WHEEL
performance_analysis-0.1.0.dist-info/METADATA
performance_analysis-0.1.0.dist-info/RECORD
